Metadata-Version: 2.1
Name: label-mapper
Version: 0.0.1
Summary: A spaCy extension to map NER labels.
Author: WJB Mattingly
